[
	{
		"inputs": [
			{
				"internalType": "uint256",
				"name": "issueId",
				"type": "uint256"
			}
		],
		"name": "closeIssue",
		"outputs": [],
		"stateMutability": "nonpayable",
		"type": "function"
	},
	{
		"inputs": [],
		"stateMutability": "nonpayable",
		"type": "constructor"
	},
	{
		"anonymous": false,
		"inputs": [
			{
				"indexed": false,
				"internalType": "uint256",
				"name": "issueId",
				"type": "uint256"
			},
			{
				"indexed": false,
				"internalType": "string",
				"name": "description",
				"type": "string"
			},
			{
				"indexed": false,
				"internalType": "uint256",
				"name": "yesCount",
				"type": "uint256"
			},
			{
				"indexed": false,
				"internalType": "uint256",
				"name": "noCount",
				"type": "uint256"
			}
		],
		"name": "IssueClosed",
		"type": "event"
	},
	{
		"anonymous": false,
		"inputs": [
			{
				"indexed": false,
				"internalType": "uint256",
				"name": "issueId",
				"type": "uint256"
			},
			{
				"indexed": false,
				"internalType": "string",
				"name": "description",
				"type": "string"
			},
			{
				"indexed": false,
				"internalType": "uint256",
				"name": "closeTimestamp",
				"type": "uint256"
			}
		],
		"name": "IssueOpened",
		"type": "event"
	},
	{
		"inputs": [
			{
				"internalType": "string",
				"name": "_description",
				"type": "string"
			}
		],
		"name": "openIssue",
		"outputs": [],
		"stateMutability": "nonpayable",
		"type": "function"
	},
	{
		"inputs": [
			{
				"internalType": "uint256",
				"name": "issueId",
				"type": "uint256"
			},
			{
				"internalType": "bool",
				"name": "voteYes",
				"type": "bool"
			}
		],
		"name": "vote",
		"outputs": [],
		"stateMutability": "nonpayable",
		"type": "function"
	},
	{
		"anonymous": false,
		"inputs": [
			{
				"indexed": false,
				"internalType": "uint256",
				"name": "issueId",
				"type": "uint256"
			},
			{
				"indexed": false,
				"internalType": "address",
				"name": "voter",
				"type": "address"
			},
			{
				"indexed": false,
				"internalType": "bool",
				"name": "voteYes",
				"type": "bool"
			}
		],
		"name": "Voted",
		"type": "event"
	},
	{
		"inputs": [],
		"name": "admin",
		"outputs": [
			{
				"internalType": "address",
				"name": "",
				"type": "address"
			}
		],
		"stateMutability": "view",
		"type": "function"
	},
	{
		"inputs": [
			{
				"internalType": "uint256",
				"name": "issueId",
				"type": "uint256"
			}
		],
		"name": "getIssue",
		"outputs": [
			{
				"internalType": "string",
				"name": "description",
				"type": "string"
			},
			{
				"internalType": "bool",
				"name": "isOpen",
				"type": "bool"
			},
			{
				"internalType": "uint256",
				"name": "yesCount",
				"type": "uint256"
			},
			{
				"internalType": "uint256",
				"name": "noCount",
				"type": "uint256"
			},
			{
				"internalType": "uint256",
				"name": "closeTimestamp",
				"type": "uint256"
			}
		],
		"stateMutability": "view",
		"type": "function"
	},
	{
		"inputs": [],
		"name": "issueCount",
		"outputs": [
			{
				"internalType": "uint256",
				"name": "",
				"type": "uint256"
			}
		],
		"stateMutability": "view",
		"type": "function"
	},
	{
		"inputs": [
			{
				"internalType": "uint256",
				"name": "",
				"type": "uint256"
			}
		],
		"name": "issues",
		"outputs": [
			{
				"internalType": "string",
				"name": "description",
				"type": "string"
			},
			{
				"internalType": "bool",
				"name": "isOpen",
				"type": "bool"
			},
			{
				"internalType": "uint256",
				"name": "yesCount",
				"type": "uint256"
			},
			{
				"internalType": "uint256",
				"name": "noCount",
				"type": "uint256"
			},
			{
				"internalType": "uint256",
				"name": "closeTimestamp",
				"type": "uint256"
			}
		],
		"stateMutability": "view",
		"type": "function"
	}
]